custom_profiler/__init__.py
custom_profiler/collecteur.py
custom_profiler/custum_logger.py
custom_profiler/custum_profiler.py
custom_profiler/human_readable_time.py
custom_profiler/line_by_line.py
custom_profiler-0.3.0.dist-info/METADATA
custom_profiler-0.3.0.dist-info/WHEEL
custom_profiler-0.3.0.dist-info/top_level.txt
custom_profiler-0.3.0.dist-info/RECORD
